qaml/__init__.py
qaml/__main__.py
qaml/cli_agent.py
qaml/client.py
qaml-0.0.8.2.dist-info/LICENSE
qaml-0.0.8.2.dist-info/METADATA
qaml-0.0.8.2.dist-info/WHEEL
qaml-0.0.8.2.dist-info/entry_points.txt
qaml-0.0.8.2.dist-info/top_level.txt
qaml-0.0.8.2.dist-info/RECORD
