Metadata-Version: 2.1
Name: qaml
Version: 0.0.8.2
Summary: Control your devices with natural language
Author-email: Miguel Salinas <miguel@camelqa.com>
Project-URL: Homepage, https://github.com/qaml-ai/qaml-python
Classifier: Programming Language :: Python :: 3
Classifier: License :: OSI Approved :: MIT License
Classifier: Operating System :: OS Independent
Requires-Python: >=3.7
License-File: LICENSE
Requires-Dist: Appium-Python-Client >=4.0.0
Requires-Dist: Pillow >=10.2
Requires-Dist: requests >=2.31
